merge_project_diff/__init__.py
merge_project_diff/__main__.py
merge_project_diff/manifest_diff.py
merge_project_diff/merge_project_files.py
merge_project_diff/merge_public.py
merge_project_diff/merge_xml_diff.py
projectdiff_tyj-1.1.0.dist-info/LICENSE
projectdiff_tyj-1.1.0.dist-info/METADATA
projectdiff_tyj-1.1.0.dist-info/WHEEL
projectdiff_tyj-1.1.0.dist-info/entry_points.txt
projectdiff_tyj-1.1.0.dist-info/top_level.txt
projectdiff_tyj-1.1.0.dist-info/RECORD
